filesizeview/filesizeview.py
filesizeview-0.0.8.dist-info/METADATA
filesizeview-0.0.8.dist-info/WHEEL
filesizeview-0.0.8.dist-info/entry_points.txt
filesizeview-0.0.8.dist-info/top_level.txt
filesizeview-0.0.8.dist-info/RECORD
