Metadata-Version: 2.1
Name: filesizeview
Version: 0.0.8
Summary: Graphical display of file sizes on terminal
Home-page: https://github.com/heiner/filesizeview
Requires-Python: >=3.0
